{
    "1017857d-6f14-0883-a837-159be76bebd2": {
        "paletteKey": "FlexLayoutCol",
        "designerReference": [
            {
                "_key": "style",
                "_value": "margin: 20px;",
                "_type": "kv",
                "_attrDef": "p"
            },
            {
                "_key": "class",
                "_value": "",
                "_type": "kv",
                "_attrDef": "p"
            },
            {
                "_key": "fxFlex",
                "_value": "",
                "_type": "kv",
                "_attrDef": "p"
            },
            {
                "_key": "fxLayoutGap",
                "_value": "",
                "_type": "kv",
                "_attrDef": "p"
            },
            {
                "_key": "wrap",
                "_value": "wrap",
                "_type": "a",
                "_attrDef": "p"
            },
            {
                "_key": "layoutAlign",
                "_value": "start",
                "_type": "a",
                "_attrDef": "p"
            },
            {
                "_key": "pLayoutAlign",
                "_value": "stretch",
                "_type": "a",
                "_attrDef": "p"
            },
            {
                "_key": "fxShow",
                "_value": "true",
                "_type": "kv",
                "_attrDef": "p"
            },
            {
                "_key": "fxHide",
                "_value": "false",
                "_type": "kv",
                "_attrDef": "p"
            }
        ],
        "d1532f43-df0b-0757-cb47-c8e96de628ca": {
            "paletteKey": "FlexLayoutCol",
            "designerReference": [
                {
                    "_key": "style",
                    "_value": "",
                    "_type": "kv",
                    "_attrDef": "p"
                },
                {
                    "_key": "class",
                    "_value": "",
                    "_type": "kv",
                    "_attrDef": "p"
                },
                {
                    "_key": "fxFlex",
                    "_value": "",
                    "_type": "kv",
                    "_attrDef": "p"
                },
                {
                    "_key": "fxLayoutGap",
                    "_value": "",
                    "_type": "kv",
                    "_attrDef": "p"
                },
                {
                    "_key": "wrap",
                    "_value": "wrap",
                    "_type": "a",
                    "_attrDef": "p"
                },
                {
                    "_key": "layoutAlign",
                    "_value": "start",
                    "_type": "a",
                    "_attrDef": "p"
                },
                {
                    "_key": "pLayoutAlign",
                    "_value": "stretch",
                    "_type": "a",
                    "_attrDef": "p"
                },
                {
                    "_key": "fxShow",
                    "_value": "true",
                    "_type": "kv",
                    "_attrDef": "p"
                },
                {
                    "_key": "fxHide",
                    "_value": "false",
                    "_type": "kv",
                    "_attrDef": "p"
                }
            ],
            "e1daeed9-0d93-68f8-e5dc-a0e4d69b7032": {
                "paletteKey": "NG-H2",
                "designerReference": [
                    {
                        "_key": "style",
                        "_value": "",
                        "_type": "kv",
                        "_attrDef": "p"
                    },
                    {
                        "_key": "class",
                        "_value": "",
                        "_type": "kv",
                        "_attrDef": "p"
                    },
                    {
                        "_key": "H2 Text",
                        "_value": "HR Policies",
                        "_type": "a",
                        "_attrDef": "p"
                    }
                ]
            }
        },
        "81c5c80e-61e1-388e-8fb7-412552ccd818": {
            "paletteKey": "FlexLayoutCol",
            "designerReference": [
                {
                    "_key": "style",
                    "_value": "",
                    "_type": "kv",
                    "_attrDef": "p"
                },
                {
                    "_key": "class",
                    "_value": "",
                    "_type": "kv",
                    "_attrDef": "p"
                },
                {
                    "_key": "fxFlex",
                    "_value": "",
                    "_type": "kv",
                    "_attrDef": "p"
                },
                {
                    "_key": "fxLayoutGap",
                    "_value": "",
                    "_type": "kv",
                    "_attrDef": "p"
                },
                {
                    "_key": "wrap",
                    "_value": "wrap",
                    "_type": "a",
                    "_attrDef": "p"
                },
                {
                    "_key": "layoutAlign",
                    "_value": "start",
                    "_type": "a",
                    "_attrDef": "p"
                },
                {
                    "_key": "pLayoutAlign",
                    "_value": "stretch",
                    "_type": "a",
                    "_attrDef": "p"
                },
                {
                    "_key": "fxShow",
                    "_value": "true",
                    "_type": "kv",
                    "_attrDef": "p"
                },
                {
                    "_key": "fxHide",
                    "_value": "false",
                    "_type": "kv",
                    "_attrDef": "p"
                }
            ],
            "55fa31c7-6bed-38c7-3c99-ba872bbde748": {
                "paletteKey": "HTML",
                "designerReference": [
                    {
                        "_key": "style",
                        "_value": "",
                        "_type": "kv",
                        "_attrDef": "p"
                    },
                    {
                        "_key": "class",
                        "_value": "",
                        "_type": "kv",
                        "_attrDef": "p"
                    },
                    {
                        "_key": "html",
                        "_value": "<mat-form-field>\r\n  <input matInput (keyup)=\"applyFilter($event.target.value)\" placeholder=\"Filter\">\r\n</mat-form-field>\r\n\r\n<table mat-table [dataSource]=\"dataSource\" class=\"mat-elevation-z8\">\r\n\r\n\r\n  <!-- Name Column -->\r\n  <ng-container matColumnDef=\"name\">\r\n    <th mat-header-cell *matHeaderCellDef> Policy Name </th>\r\n    <td mat-cell *matCellDef=\"let element\"> {{element.title}} </td>\r\n  </ng-container>\r\n\r\n  <!-- Symbol Column -->\r\n  <ng-container matColumnDef=\"symbol\">\r\n    <th mat-header-cell *matHeaderCellDef> Category </th>\r\n    <td mat-cell *matCellDef=\"let element\"> {{element.category}} </td>\r\n  </ng-container>\r\n\r\n  <tr mat-header-row *matHeaderRowDef=\"displayedColumns\"></tr>\r\n  <tr mat-row *matRowDef=\"let row; columns: displayedColumns;\" (click)=\"selectedPolicy(row)\" style=\"cursor:pointer\"></tr>\r\n</table>\r\n",
                        "_type": "a",
                        "_attrDef": "p"
                    }
                ]
            }
        }
    }
}
